{
  "METADATA_VERSION": 20002,
  "allow_disabled_algorithms": false,
  "app-arm64-release-unsigned-signed.apk": {
    "hash": "a8293e8ffa117379fbd7abe5681b1d49a402997e67be9b5b80d038ff7dd755fe",
    "hashType": "sha256",
    "uses-permission": [
      [
        "android.permission.INTERNET",
        null
      ],
      [
        "android.permission.POST_NOTIFICATIONS",
        null
      ],
      [
        "android.permission.RECEIVE_BOOT_COMPLETED",
        null
      ],
      [
        "android.permission.ACCESS_NOTIFICATION_POLICY",
        null
      ],
      [
        "android.permission.FOREGROUND_SERVICE",
        null
      ],
      [
        "android.permission.FOREGROUND_SERVICE_DATA_SYNC",
        null
      ],
      [
        "android.permission.WAKE_LOCK",
        null
      ],
      [
        "android.permission.BATTERY_STATS",
        null
      ],
      [
        "android.permission.ACCESS_NETWORK_STATE",
        null
      ],
      [
        "com.joris.friday.DYNAMIC_RECEIVER_NOT_EXPORTED_PERMISSION",
        null
      ]
    ],
    "uses-permission-sdk-23": [],
    "features": [],
    "icons_src": {},
    "icons": {},
    "antiFeatures": {},
    "packageName": "com.joris.friday",
    "versionCode": 1002003,
    "name": "Friday",
    "versionName": "1.2.3",
    "minSdkVersion": 24,
    "targetSdkVersion": 36,
    "nativecode": [
      "arm64-v8a"
    ],
    "sig": "4ce727eccd89c0bef16a0dfad1f8fe33",
    "signer": "a78c487208a97ffb2dadf9a69bdec2a6c0050b2f99ef528ed43a01dd5c5687a3",
    "size": 11032777,
    "apkName": "app-arm64-release-unsigned-signed.apk",
    "added": 1776076413.0
  }
}